sla/__init__.py
sla/core.py
sla/utils.py
sla-1.4.1.dist-info/LICENSE
sla-1.4.1.dist-info/METADATA
sla-1.4.1.dist-info/WHEEL
sla-1.4.1.dist-info/top_level.txt
sla-1.4.1.dist-info/RECORD
