Metadata-Version: 2.1
Name: sla
Version: 1.4.1
Summary: Non-parametric LOSVD analysis for galaxy spectra
Home-page: https://github.com/gasymovdf/sla
Author: Gasymov Damir
Author-email: gasymov.df18@physics.msu.ru
Classifier: Programming Language :: Python :: 3
Classifier: License :: OSI Approved :: MIT License
Classifier: Operating System :: OS Independent
License-File: LICENSE
Requires-Dist: pseudoslit ==0.0.2
Requires-Dist: numpy ==1.21.4
Requires-Dist: scipy ==1.7.3
Requires-Dist: matplotlib ==3.5.1
Requires-Dist: astropy ==5.0
Requires-Dist: lmfit ==1.0.3
Requires-Dist: vorbin ==3.1.4
Requires-Dist: glob2 ==0.7
Requires-Dist: PyPDF2 ==1.26.0
Requires-Dist: tqdm ==4.62.3
